logri/__init__.py
logri/__main__.py
logri/management.py
logri-0.0.1.dist-info/LICENSE
logri-0.0.1.dist-info/METADATA
logri-0.0.1.dist-info/WHEEL
logri-0.0.1.dist-info/entry_points.txt
logri-0.0.1.dist-info/top_level.txt
logri-0.0.1.dist-info/RECORD
