Metadata-Version: 2.2
Name: logri
Version: 0.0.1
Summary: logri planned to be a full-featured verilog simulator
Author-email: Obvodny <obvodny@yeah.net>
Maintainer-email: Obvodny <obvodny@yeah.net>
License: 木兰宽松许可证，第2版
Keywords: verilog
Classifier: Development Status :: 1 - Planning
Classifier: Environment :: Console
Classifier: License :: OSI Approved :: Mulan Permissive Software License v2 (MulanPSL-2.0)
Classifier: Operating System :: OS Independent
Classifier: Programming Language :: Python :: 3
Classifier: Topic :: Scientific/Engineering :: Electronic Design Automation (EDA)
Requires-Python: >=3.9
License-File: LICENSE
